{
  "task": "pressure_surface_only",
  "loss": "MSE",
  "nb_parameters": 65625.0,
  "time_elapsed": 929.2912156581879,
  "hparams": {
    "encoder": [
      7,
      64,
      64,
      8
    ],
    "decoder": [
      8,
      64,
      64,
      1
    ],
    "layer": "SAGE",
    "pool": "random",
    "nb_scale": 5,
    "pool_ratio": [
      0.5,
      0.5,
      0.5,
      0.5
    ],
    "list_r": [
      0.05,
      0.2,
      0.5,
      1,
      10
    ],
    "size_hidden_layers": 8,
    "batchnorm": true,
    "res": false,
    "batch_size": 1,
    "nb_epochs": 398,
    "lr": 0.001,
    "max_neighbors": 64,
    "subsampling": 32000,
    "r": 0.05
  },
  "train_loss": 0.0011707311496138573,
  "val_loss": 0.033972924696354316
}